onionpaper/__init__.py
onionpaper/__main__.py
onionpaper/core.py
onionpaper/ctypes.py
onionpaper/tween.py
onionpaper-0.4.0.dist-info/LICENSE
onionpaper-0.4.0.dist-info/METADATA
onionpaper-0.4.0.dist-info/WHEEL
onionpaper-0.4.0.dist-info/top_level.txt
onionpaper-0.4.0.dist-info/RECORD
