Metadata-Version: 2.1
Name: onionpaper
Version: 0.4.0
Summary: Onion Paper
Author-email: Elmer Nocon <elmernocon@gmail.com>
License: MIT License
Requires-Python: >=3.9
License-File: LICENSE
Requires-Dist: click
Requires-Dist: humanfriendly
Requires-Dist: PyAutoGUI
Requires-Dist: pytweening
Requires-Dist: PyYAML
Provides-Extra: dev
Requires-Dist: black ; extra == 'dev'
Requires-Dist: build ; extra == 'dev'
Requires-Dist: twine ; extra == 'dev'
Provides-Extra: test
